input-validation/__init__.py
input-validation/validator.py
inputvalidation/__init__.py
inputvalidation/validator.py
inputvalidation_ssa3512-0.0.1.dist-info/LICENSE
inputvalidation_ssa3512-0.0.1.dist-info/METADATA
inputvalidation_ssa3512-0.0.1.dist-info/WHEEL
inputvalidation_ssa3512-0.0.1.dist-info/top_level.txt
inputvalidation_ssa3512-0.0.1.dist-info/RECORD
