Metadata-Version: 2.1
Name: inputvalidation-ssa3512
Version: 0.0.1
Summary: Simply console input validation
Home-page: https://github.com/ssa3512/input-validation
Author: Steve Ashman
Author-email: steve@ash.mn
License: UNKNOWN
Platform: UNKNOWN
Classifier: Programming Language :: Python :: 3
Classifier: License :: OSI Approved :: MIT License
Classifier: Operating System :: OS Independent
Requires-Python: >=3.8
